ttcrpy-1.3.4.dist-info/WHEEL
ttcrpy-1.3.4.dist-info/top_level.txt
ttcrpy-1.3.4.dist-info/RECORD
ttcrpy-1.3.4.dist-info/METADATA
ttcrpy/rgrid.cpython-38-x86_64-linux-gnu.so
ttcrpy/tmesh.cpython-38-x86_64-linux-gnu.so
ttcrpy/_version.py
ttcrpy/__init__.py
