Metadata-Version: 2.1
Name: ttcrpy
Version: 1.3.4
Summary: Code to perform raytracing for geophysical applications
Author-email: Bernard Giroux <bernard.giroux@inrs.ca>
License:                     GNU GENERAL PUBLIC LICENSE
Project-URL: homepage, https://github.com/groupeLIAMG/ttcr
Project-URL: documentation, https://ttcrpy.readthedocs.io/en/latest/
Classifier: Development Status :: 4 - Beta
Classifier: Intended Audience :: Science/Research
Classifier: Intended Audience :: Education
Classifier: License :: OSI Approved :: GNU General Public License v3 or later (GPLv3+)
Classifier: Operating System :: OS Independent
Classifier: Programming Language :: C++
Classifier: Programming Language :: Cython
Classifier: Programming Language :: Python :: 3.8
Classifier: Programming Language :: Python :: 3.9
Classifier: Programming Language :: Python :: 3.10
Classifier: Programming Language :: Python :: 3.11
Classifier: Topic :: Scientific/Engineering
Requires-Python: >=3.8
